LICENSE
triqler/__init__.py
triqler/__main__.py
triqler/convert/__init__.py
triqler/convert/diann.py
triqler/convert/dinosaur.py
triqler/convert/helpers.py
triqler/convert/maxquant.py
triqler/convert/normalize_intensities.py
triqler/convert/percolator.py
triqler/convert/quandenser.py
triqler/convolution_dp.py
triqler/diff_exp.py
triqler/distribution/__init__.py
triqler/distribution/plot_hyperparameter_fits.py
triqler/distribution/plot_posteriors.py
triqler/hyperparameters.py
triqler/parsers.py
triqler/pgm.py
triqler/qvality.py
triqler/triqler.py
triqler-0.9.1.dist-info/LICENSE
triqler-0.9.1.dist-info/METADATA
triqler-0.9.1.dist-info/WHEEL
triqler-0.9.1.dist-info/entry_points.txt
triqler-0.9.1.dist-info/RECORD
