Metadata-Version: 2.1
Name: triqler
Version: 0.9.1
Summary: Triqler: TRansparent Identification-Quantification-Linked Error Rates
Home-page: https://github.com/statisticalbiotechnology/triqler
License: Apache-2.0
Keywords: mass spectrometry,missing values,proteomics,quantification
Author: Matthew The
Author-email: matthew.the@tum.de
Requires-Python: >=3.10,<3.14
Classifier: License :: OSI Approved :: Apache Software License
Classifier: Programming Language :: Python :: 3
Classifier: Programming Language :: Python :: 3.10
Classifier: Programming Language :: Python :: 3.11
Classifier: Programming Language :: Python :: 3.12
Requires-Dist: job-pool (>=0.3.0)
Requires-Dist: numpy (>=2.0.0,<3.0.0)
Requires-Dist: pandas (>=1.4.0)
Requires-Dist: pyarrow (>=19.0.1)
Requires-Dist: scipy (>=1.9.1,<2.0.0)
Requires-Dist: threadpoolctl (>=3.1.0,<4.0.0)
Project-URL: Repository, https://github.com/statisticalbiotechnology/triqler
